heare/histograms/__init__.py
heare_histograms-0.1.3.dist-info/LICENSE
heare_histograms-0.1.3.dist-info/METADATA
heare_histograms-0.1.3.dist-info/WHEEL
heare_histograms-0.1.3.dist-info/RECORD
