Metadata-Version: 2.1
Name: heare-histograms
Version: 0.1.3
Summary: Pure python histogram implementation for analysis and prediction.
License: MIT
Author: Sean Fitzgerald
Author-email: sean@fitzgeralds.me
Requires-Python: >=3.11,<4.0
Classifier: License :: OSI Approved :: MIT License
Classifier: Programming Language :: Python :: 3
Classifier: Programming Language :: Python :: 3.11
Classifier: Programming Language :: Python :: 3.12
